osmosis_protobuf/.gitignore
osmosis_protobuf/__init__.py
osmosis_protobuf/__init__.pyi
osmosis_protobuf/proofs.proto
osmosis_protobuf/proofs_pb2.py
osmosis_protobuf/proofs_pb2.pyi
osmosis_protobuf/amino/__init__.py
osmosis_protobuf/amino/__init__.pyi
osmosis_protobuf/amino/amino.proto
osmosis_protobuf/amino/amino_pb2.py
osmosis_protobuf/amino/amino_pb2.pyi
osmosis_protobuf/cosmos/__init__.py
osmosis_protobuf/cosmos/__init__.pyi
osmosis_protobuf/cosmos/app/__init__.py
osmosis_protobuf/cosmos/app/__init__.pyi
osmosis_protobuf/cosmos/app/runtime/__init__.py
osmosis_protobuf/cosmos/app/runtime/__init__.pyi
osmosis_protobuf/cosmos/app/runtime/v1alpha1/__init__.py
osmosis_protobuf/cosmos/app/runtime/v1alpha1/__init__.pyi
osmosis_protobuf/cosmos/app/runtime/v1alpha1/module.proto
osmosis_protobuf/cosmos/app/runtime/v1alpha1/module_pb2.py
osmosis_protobuf/cosmos/app/runtime/v1alpha1/module_pb2.pyi
osmosis_protobuf/cosmos/app/v1alpha1/__init__.py
osmosis_protobuf/cosmos/app/v1alpha1/__init__.pyi
osmosis_protobuf/cosmos/app/v1alpha1/config.proto
osmosis_protobuf/cosmos/app/v1alpha1/config_pb2.py
osmosis_protobuf/cosmos/app/v1alpha1/config_pb2.pyi
osmosis_protobuf/cosmos/app/v1alpha1/module.proto
osmosis_protobuf/cosmos/app/v1alpha1/module_pb2.py
osmosis_protobuf/cosmos/app/v1alpha1/module_pb2.pyi
osmosis_protobuf/cosmos/app/v1alpha1/query.proto
osmosis_protobuf/cosmos/app/v1alpha1/query_grpc.py
osmosis_protobuf/cosmos/app/v1alpha1/query_pb2.py
osmosis_protobuf/cosmos/app/v1alpha1/query_pb2.pyi
osmosis_protobuf/cosmos/app/v1alpha1/query_pb2_grpc.py
osmosis_protobuf/cosmos/auth/__init__.py
osmosis_protobuf/cosmos/auth/__init__.pyi
osmosis_protobuf/cosmos/auth/module/__init__.py
osmosis_protobuf/cosmos/auth/module/__init__.pyi
osmosis_protobuf/cosmos/auth/module/v1/__init__.py
osmosis_protobuf/cosmos/auth/module/v1/__init__.pyi
osmosis_protobuf/cosmos/auth/module/v1/module.proto
osmosis_protobuf/cosmos/auth/module/v1/module_pb2.py
osmosis_protobuf-0.4.0.dist-info/METADATA
osmosis_protobuf-0.4.0.dist-info/WHEEL
osmosis_protobuf-0.4.0.dist-info/RECORD
